{"updatedAt":"2025-07-09T20:38:40.000Z","createdAt":"2025-06-20T15:55:08.918Z","id":"43WEsqIvPbDBrleC","name":"DISCO HubSpot PM update Deal","active":false,"isArchived":false,"nodes":[{"parameters":{"content":"# Update HubSpot Deal\n* Updates HubSpot \"Keywords\" with the OIDs from OS3 triggered by Jira \n* Updates \"Offer IDs\" Object of Deal (Perf Mktg only)\n","height":220,"width":520},"type":"n8n-nodes-base.stickyNote","position":[-340,-180],"typeVersion":1,"id":"58473e0b-96f5-45a2-8d0b-7a320792fa85","name":"Sticky Note"},{"parameters":{"authentication":"appToken","resource":"deal","operation":"get","dealId":{"__rl":true,"value":"={{ $('setWebhookVars').item.json.hs_deal_id }}","mode":"id"},"filters":{"propertiesCollection":{"propertiesValues":{"properties":["offer_ids"],"propertyMode":"valueOnly"}}}},"type":"n8n-nodes-base.hubspot","typeVersion":2.1,"position":[160,100],"id":"1ac542a1-1cbb-4fa2-b252-1300ab111b5d","name":"hsGETDeal","credentials":{"hubspotAppToken":{"id":"g2yPcP4yBsSlHE4S","name":"HubSpot: N8N-SANDBOX-DISCO-2025_0623a"}}},{"parameters":{"authentication":"appToken","resource":"deal","operation":"update","dealId":{"__rl":true,"value":"={{ $json.dealId }}","mode":"id"},"updateFields":{"customPropertiesUi":{"customPropertiesValues":[{"property":"keywords","value":"={{ $json.properties.keywords.value }}\n-\nOIDs: {{ $json.offer_ids }}\n---------\nOID: {{ $('setWebhookVars').item.json.OID }}\nFrom Jira: ADO-{{ $('setWebhookVars').item.json.ADOkey }}\nupdated by n8n at : {{ $now.format('yyyy-MM-dd hh:mm') }}"}]}}},"type":"n8n-nodes-base.hubspot","typeVersion":2.1,"position":[600,100],"id":"798d3c72-f843-434d-b287-42abda4cf2fb","name":"hsUPDATEDeal","alwaysOutputData":false,"credentials":{"hubspotAppToken":{"id":"g2yPcP4yBsSlHE4S","name":"HubSpot: N8N-SANDBOX-DISCO-2025_0623a"}}},{"parameters":{"path":"jira-webhook-n8n-updateHSOID","options":{"ipWhitelist":"2401:1d80:321c:5:77a7:28ed:8777:5138, 104.23.209.105"}},"type":"n8n-nodes-base.webhook","typeVersion":2,"position":[-280,100],"id":"b1e0fe4b-8a3b-45cc-8f1b-83299edf18b4","name":"Webhook","webhookId":"3e9a60df-d215-4368-8000-99b077f96b45"},{"parameters":{"assignments":{"assignments":[{"id":"e55494ff-e803-4586-8fae-05c2683c90e8","name":"OID","value":"={{ \n  Math.floor(Number($json.query.OID) || 0)\n}}","type":"string"},{"id":"b1ba5852-7e91-4524-8386-74f80d818bd7","name":"ADOkey","value":"={{ \n  $json.query.ADOkey === null || $json.query.ADOkey === \"\" ? \n    null : \n    (\n      Number(String($json.query.ADOkey).replace(/[^0-9]/g, '')) || null\n    )\n}}","type":"string"},{"id":"90255888-b225-4316-bb13-e5828ab28944","name":"webhookUrl","value":"={{ $json.webhookUrl }}","type":"string"},{"id":"24aa3da7-69b4-4e98-b76f-6b180e023720","name":"hs_deal_id","value":"={{ \n  Math.floor(Number($json.query.OID) || 39262839315 )\n}}","type":"number"}]},"options":{}},"type":"n8n-nodes-base.set","typeVersion":3.4,"position":[-60,100],"id":"9ecd7ecc-1970-482a-9c2b-04f093bb9a60","name":"setWebhookVars"},{"parameters":{"content":"### HubSpot Sandbox Creds\n[HubSpot](https://app.hubspot.com/private-apps/40213119/14859713)\n### Pipelines\n* $vars.hubspotPipeline_insights_PRODUCTION \n* $vars.hubspotPipeline_insights_sandbox  \n* $vars.hubspotPipeline_perfmktg_PRODUCTION \n* $vars.hubspotPipeline_perfmktg_sandbox","height":200,"width":480,"color":3},"type":"n8n-nodes-base.stickyNote","position":[-20,280],"typeVersion":1,"id":"9a66ac11-7bc9-4319-822a-ff3f39327b91","name":"Sticky Note2"},{"parameters":{"assignments":{"assignments":[{"id":"c70b15a8-6979-4b88-a7d0-1d114a659e20","name":"=keywords","value":"={{ $json.properties.keywords.value }}","type":"string"},{"id":"2264d1e9-a22f-4aa0-9688-5a303db172bd","name":"dealId","value":"={{ $json.dealId }}","type":"string"},{"id":"2a734716-df3a-4f87-ae9e-1d4099fdb79c","name":"offer_ids","value":"={{ $json.properties.offer_ids.value }}","type":"string"}]},"options":{}},"type":"n8n-nodes-base.set","typeVersion":3.4,"position":[380,100],"id":"cb8faaf1-e175-41a4-bcf6-764820183578","name":"Edit Fields"},{"parameters":{"content":"## WIP Version\n* Change HubSpot Creds to PRODUCTION vs sandbox\n","height":220,"width":520,"color":7},"type":"n8n-nodes-base.stickyNote","position":[200,-180],"typeVersion":1,"id":"d61c6696-4baf-4626-904e-5d03f031c5e6","name":"Sticky Note1"}],"connections":{"hsGETDeal":{"main":[[{"node":"Edit Fields","type":"main","index":0}]]},"hsUPDATEDeal":{"main":[[]]},"Webhook":{"main":[[{"node":"setWebhookVars","type":"main","index":0}]]},"setWebhookVars":{"main":[[{"node":"hsGETDeal","type":"main","index":0}]]},"Edit Fields":{"main":[[{"node":"hsUPDATEDeal","type":"main","index":0}]]}},"settings":{"executionOrder":"v1","callerPolicy":"workflowsFromSameOwner","executionTimeout":600},"staticData":null,"meta":{"templateCredsSetupCompleted":true},"pinData":{"Webhook":[{"json":{"headers":{"host":"prodegellc.app.n8n.cloud","user-agent":"Automation for Jira AC app/1.0;d72d0e88-4494-42f7-bbac-6acb1ed7c58f","accept":"application/json; charset=UTF-8, */*;q=0.8","accept-encoding":"gzip, br","adokey":"ADO-1757","cdn-loop":"cloudflare; loops=1; subreqs=1","cf-connecting-ip":"2401:1d80:321c:5:77a7:28ed:8777:5138","cf-ew-via":"15","cf-ipcountry":"US","cf-ray":"952f154b4358b83d-IAD","cf-visitor":"{\"scheme\":\"https\"}","cf-worker":"n8n.cloud","content-type":"application/json","hs_deal_id":"","oid":"","x-b3-sampled":"0","x-b3-spanid":"5848b034274556d7","x-b3-traceid":"6831dc65d6453ff766a81424a237b896","x-forwarded-for":"2401:1d80:321c:5:77a7:28ed:8777:5138, 104.23.209.105","x-forwarded-host":"prodegellc.app.n8n.cloud","x-forwarded-port":"443","x-forwarded-proto":"https","x-forwarded-server":"traefik-prod-users-gwc-30-6d57d45df-x2ghq","x-is-trusted":"yes","x-real-ip":"2401:1d80:321c:5:77a7:28ed:8777:5138"},"params":{},"query":{"OID":"","ADOkey":"ADO-1757","hs_deal_id":""},"body":{},"webhookUrl":"https://prodegellc.app.n8n.cloud/webhook/jira-webhook-n8n-updateHSOID","executionMode":"production"}}]},"versionId":"63a1349e-b422-4b95-ac82-89f82010713c","activeVersionId":null,"triggerCount":1,"shared":[{"updatedAt":"2025-06-24T02:13:08.948Z","createdAt":"2025-06-24T02:13:08.948Z","role":"workflow:owner","workflowId":"43WEsqIvPbDBrleC","projectId":"NOrA7nVi3G84Nq0v"}],"activeVersion":null,"tags":[{"updatedAt":"2025-03-27T02:22:51.862Z","createdAt":"2025-03-27T02:22:51.862Z","id":"588qevcpi6N20eWF","name":"test"},{"updatedAt":"2025-06-06T18:17:40.197Z","createdAt":"2025-06-06T18:17:16.177Z","id":"QSobdHvedr4NOCqq","name":"hubspot HS"},{"updatedAt":"2025-06-06T18:17:45.414Z","createdAt":"2025-05-20T18:50:07.486Z","id":"o9kQdq2i4tcW3ACG","name":"disco PM"}]}